{
	"variants": {
		"burning=false,facing=north": {
			"model": "practicaladjustments:furnace_iron"
		},
		"burning=false,facing=south": {
			"model": "practicaladjustments:furnace_iron", "y": 180
		},
		"burning=false,facing=west": {
			"model": "practicaladjustments:furnace_iron", "y": 270
		},
		"burning=false,facing=east": {
			"model": "practicaladjustments:furnace_iron", "y": 90
		},
		"burning=true,facing=north": {
			"model": "practicaladjustments:furnace_iron_burning"
		},
		"burning=true,facing=south": {
			"model": "practicaladjustments:furnace_iron_burning", "y": 180
		},
		"burning=true,facing=west": {
			"model": "practicaladjustments:furnace_iron_burning", "y": 270
		},
		"burning=true,facing=east": {
			"model": "practicaladjustments:furnace_iron_burning", "y": 90
		}
	}
}